Workbook

Sheet Dashboard
A1: Allegro Business Performance Dashboard
A3: Quarterly Performance Overview | Q1 2024 – Q2 2026
A5: GMV – Group (PLN m) | C5: Revenue ( PLN m ) | E5: Adjusted EBITDA ( PLN m ) | G5: Active Buyers - Group ( m ) | I5: GMV / Active Buyer ( PLN, LTM )
A6: =Source_Data!G11 -> 19571.763 | C6: =Source_Data!J11 -> 3339.458 | E6: =Source_Data!K11 -> 1030.14 | G6: =Source_Data!D11 -> 20.858239 | I6: =Source_Data!N11 -> 3528.194
A8: YoY | B8: =KPI_Analysis!B7 -> 0.1438139 | C8: YoY | D8: =KPI_Analysis!C7 -> 0.16126988 | E8: YoY | F8: =KPI_Analysis!D7 -> 0.11537712 | G8: YoY | H8: =KPI_Analysis!E7 -> 0.016351385 | I8: YoY | J8: =KPI_Analysis!F7 -> 0.097693725
A40: KEY INSIGHTS - Q2 2026
A42: 1. Stron GMV Growthg GMV increased by 14.38% YoY in Q2 2026, indicating continued growth in marketplace transaction value.
A46: 2. Revenue Growth Outpaced GMV Revenue increased by 16.13% YoY in Q2 2026, outpacing GMV growth of 14.38%. This indicates improved revenue generation relative to transaction value.
A50: 3. Positive Adjusted EBITDA Growth Adjusted EBITDA increased by 11.54% YoY in Q2 2026. However, its growth was slower than revenue growth of 16.13%.
A54: 4. Higher GMV per Active Buyer Active buyers increased by 1.64% YoY, while GMV per active buyer (LTM) grew by 9.77%. This suggests that higher spending per buyer contributed to overall GMV growth.
A58: 5. Overall Business Performance In Q2 2026, Allegro demonstrated growth across GMV, revenue, and Adjusted EBITDA. Revenue growth outpaced GMV, while higher GMV per active buyer contributed to overall marketplace growth.

Sheet KPI_Analysis
A1: Period | B1: GMV YoY | C1: Revenue YoY | D1: Adjusted EBITDA YoY | E1: Active Buyers YoY | F1: GMV per Active Buyer YoY
A2: Q1 2025 | B2: =Source_Data!G6/Source_Data!G2-1 -> 0.081715095 | C2: =Source_Data!J6/Source_Data!J2-1 -> 0.068297409 | D2: =Source_Data!K6/Source_Data!K2-1 -> 0.055639089 | E2: =Source_Data!D6/Source_Data!D2-1 -> 0.058905341 | F2: =Source_Data!N6/Source_Data!N2-1 -> 0.035120999
A3: Q2 2025 | B3: =Source_Data!G7/Source_Data!G3-1 -> 0.091618554 | C3: =Source_Data!J7/Source_Data!J3-1 -> 0.10801947 | D3: =Source_Data!K7/Source_Data!K3-1 -> 0.19754004 | E3: =Source_Data!D7/Source_Data!D3-1 -> 0.045867089 | F3: =Source_Data!N7/Source_Data!N3-1 -> 0.042893038
A4: Q3 2025 | B4: =Source_Data!G8/Source_Data!G4-1 -> 0.09896147 | C4: =Source_Data!J8/Source_Data!J4-1 -> 0.12920866 | D4: =Source_Data!K8/Source_Data!K4-1 -> 0.23681191 | E4: =Source_Data!D8/Source_Data!D4-1 -> 0.034097853 | F4: =Source_Data!N8/Source_Data!N4-1 -> 0.054333736
A5: Q4 2025 | B5: =Source_Data!G9/Source_Data!G5-1 -> 0.092455661 | C5: =Source_Data!J9/Source_Data!J5-1 -> 0.14061765 | D5: =Source_Data!K9/Source_Data!K5-1 -> 0.10428367 | E5: =Source_Data!D9/Source_Data!D5-1 -> 0.011443261 | F5: =Source_Data!N9/Source_Data!N5-1 -> 0.079071477
A6: Q1 2026 | B6: =Source_Data!G10/Source_Data!G6-1 -> 0.12841282 | C6: =Source_Data!J10/Source_Data!J6-1 -> 0.16534595 | D6: =Source_Data!K10/Source_Data!K6-1 -> 0.23575112 | E6: =Source_Data!D10/Source_Data!D6-1 -> -0.001892335 | F6: =Source_Data!N10/Source_Data!N6-1 -> 0.10442615
A7: Q2 2026 | B7: =Source_Data!G11/Source_Data!G7-1 -> 0.1438139 | C7: =Source_Data!J11/Source_Data!J7-1 -> 0.16126988 | D7: =Source_Data!K11/Source_Data!K7-1 -> 0.11537712 | E7: =Source_Data!D11/Source_Data!D7-1 -> 0.016351385 | F7: =Source_Data!N11/Source_Data!N7-1 -> 0.097693725

Sheet Source_Data
A1: Period | B1: Year | C1: Quarter | D1: Active Buyers - Group | E1: Active Buyers - Poland | F1: Active Buyers - International | G1: GMV - Group | H1: GMV - Poland | I1: GMV - International | J1: Total Revenue | K1: Adjusted EBITDA - Group | L1: Adjusted EBITDA - Poland | M1: Adjusted EBITDA - International | N1: GMV per Active Buyer - Group | O1: Items Sold - Group | P1: Take Rate - Poland
A2: Q1 2024 | B2: =VALUE(RIGHT(A2,4)) -> 2024 | C2: =LEFT(A2,2) -> Q1 | D2: 19.27085 | E2: 14.774683 | F2: 4.496167 | G2: 14167.615 | H2: 13569.688 | I2: 597.928 | J2: 2371.027 | K2: 714.282 | L2: 819.187 | M2: -105.026 | N2: 3054.896 | O2: 304.603 | P2: 0.121771
A3: Q2 2024 | B3: =VALUE(RIGHT(A3,4)) -> 2024 | C3: =LEFT(A3,2) -> Q2 | D3: 19.622632 | E3: 14.876811 | F3: 4.745821 | G3: 15674.86 | H3: 15054.349 | I3: 632.016 | J3: 2595.347 | K3: 771.231 | L3: 908.125 | M3: -135.947 | N3: 3081.992 | O3: 326.253 | P3: 0.125328
A4: Q3 2024 | B4: =VALUE(RIGHT(A4,4)) -> 2024 | C4: =LEFT(A4,2) -> Q3 | D4: 19.83424 | E4: 14.939273 | F4: 4.894967 | G4: 15315.102 | H4: 14705.824 | I4: 621.302 | J4: 2512.262 | K4: 742.526 | L4: 882.015 | M4: -139.181 | N4: 3120.437 | O4: 325.533 | P4: 0.125104
A5: Q4 2024 | B5: =VALUE(RIGHT(A5,4)) -> 2024 | C5: =LEFT(A5,2) -> Q4 | D5: 20.180961 | E5: 15.058253 | F5: 5.122708 | G5: 18212.319 | H5: 17377.086 | I5: 844.362 | J5: 3007.318 | K5: 798.754 | L5: 973.978 | M5: -174.953 | N5: 3140.083 | O5: 371.062 | P5: 0.120114
A6: Q1 2025 | B6: =VALUE(RIGHT(A6,4)) -> 2025 | C6: =LEFT(A6,2) -> Q1 | D6: 20.406006 | E6: 15.114284 | F6: 5.291722 | G6: 15325.323 | H6: 14778.729 | I6: 549.604 | J6: 2532.962 | K6: 754.024 | L6: 858.663 | M6: -104.466 | N6: 3162.187 | O6: 343.984 | P6: 0.125815
A7: Q2 2025 | B7: =VALUE(RIGHT(A7,4)) -> 2025 | C7: =LEFT(A7,2) -> Q2 | D7: 20.522665 | E7: 15.172179 | F7: 5.350486 | G7: 17110.968 | H7: 16535.093 | I7: 579.913 | J7: 2875.695 | K7: 923.58 | L7: 1035.61 | M7: -113.435 | N7: 3214.188 | O7: 365.191 | P7: 0.130115
A8: Q3 2025 | B8: =VALUE(RIGHT(A8,4)) -> 2025 | C8: =LEFT(A8,2) -> Q3 | D8: 20.510545 | E8: 15.23182 | F8: 5.278725 | G8: 16830.707 | H8: 16231.428 | I8: 599.279 | J8: 2836.868 | K8: 918.365 | L8: 1033.702 | M8: -115.038 | N8: 3289.982 | O8: 364.224 | P8: 0.129789
A9: Q4 2025 | B9: =VALUE(RIGHT(A9,4)) -> 2025 | C9: =LEFT(A9,2) -> Q4 | D9: 20.411897 | E9: 15.348241 | F9: 5.063656 | G9: 19896.151 | H9: 18870.443 | I9: 1025.708 | J9: 3430.2 | K9: 882.051 | L9: 1054.215 | M9: -172.083 | N9: 3388.374 | O9: 401.099 | P9: 0.122629
A10: Q1 2026 | B10: =VALUE(RIGHT(A10,4)) -> 2026 | C10: =LEFT(A10,2) -> Q1 | D10: 20.367391 | E10: 15.506165 | F10: 4.897264 | G10: 17293.291 | H10: 16489.262 | I10: 804.029 | J10: 2951.777 | K10: 931.786 | L10: 1017.778 | M10: -85.943 | N10: 3492.402 | O10: 377.539 | P10: 0.126454
A11: Q2 2026 | B11: =VALUE(RIGHT(A11,4)) -> 2026 | C11: =LEFT(A11,2) -> Q2 | D11: 20.858239 | E11: 15.640527 | F11: 5.256 | G11: 19571.763 | H11: 18513.894 | I11: 1057.869 | J11: 3339.458 | K11: 1030.14 | L11: 1152.968 | M11: -122.789 | N11: 3528.194 | O11: 404.682 | P11: 0.125928

Sheet Definitions
A1: Metric | B1: Definition | C1: Unit | D1: Calculation / Notes
A2: GMV | B2: Total value of transactions on the marketplace. | C2: PLN million | D2: Reported GMV for the quarter. YoY = (Current quarter / Same quarter previous year - 1) × 100%.
A3: Revenue | B3: Total revenue generated by Allegro Group during the quarter. | C3: PLN million | D3: Reported quarterly revenue. YoY = (Current quarter / Same quarter previous year - 1) × 100%.
A4: Adjusted EBITDA | B4: Earnings before interest, taxes, depreciation and amortization, adjusted for selected items. | C4: PLN million | D4: Reported quarterly Adjusted EBITDA. YoY = (Current quarter / Same quarter previous year - 1) × 100%.
A5: Active Buyers | B5: Number of unique buyers who made at least one purchase during the last 12 months. | C5: Million buyers | D5: Reported Group active buyers (LTM). YoY = (Current quarter / Same quarter previous year - 1) × 100%.
A6: GMV per Active Buyer (LTM) | B6: Average Gross Merchandise Value per active buyer over the last 12 months. | C6: PLN per buyer | D6: Reported Group GMV per active buyer (LTM). YoY = (Current quarter / Same quarter previous year - 1) × 100%.
A8: Data Source | B8: Allegro Group — Official Investor Relations Reports
A9: Analysis Period | B9: Q1 2024 – Q2 2026 (Quarterly Data)
